grim_opt/__init__.py
grim_opt/cli_app.py
grim_opt/config.py
grim_opt/config_defaults.py
grim_opt/config_parse.py
grim_opt/helpers.py
grim_opt/land_cover.py
grim_opt/optimization.py
grim_opt/path_helpers.py
grim_opt/plot_capacities_regions.py
grim_opt/plot_capacities_totals.py
grim_opt-0.2.2.dist-info/entry_points.txt
grim_opt-0.2.2.dist-info/WHEEL
grim_opt-0.2.2.dist-info/METADATA
grim_opt-0.2.2.dist-info/RECORD
