Metadata-Version: 2.1
Name: grim-opt
Version: 0.2.2
Summary: Greenfield Renewable energy source Investment Model
Home-page: https://gitlab.tudelft.nl/nwang1/grim
License: MIT
Author: Ni Wang
Author-email: N.Wang@tudelft.nl
Requires-Python: >=3.7,<3.10
Classifier: License :: OSI Approved :: MIT License
Classifier: Programming Language :: Python :: 3
Classifier: Programming Language :: Python :: 3.7
Classifier: Programming Language :: Python :: 3.8
Classifier: Programming Language :: Python :: 3.9
Requires-Dist: OWSLib (>=0.25.0,<0.26.0)
Requires-Dist: Pillow (>=8.4.0,<9.0.0)
Requires-Dist: PyYAML (>=6.0,<7.0)
Requires-Dist: Pyomo (>=5.7.3,<6.0.0)
Requires-Dist: Shapely (>=1.7.1,<2.0.0)
Requires-Dist: geojson (>=2.5.0,<3.0.0)
Requires-Dist: matplotlib (>=3.4.1,<4.0.0)
Requires-Dist: netCDF4 (>=1.5.6,<2.0.0)
Requires-Dist: networkx (>=2.5.1,<3.0.0)
Requires-Dist: numpy (>=1.21.5,<2.0.0)
Requires-Dist: openpyxl (>=3.0.7,<4.0.0)
Requires-Dist: pandas (>=1.2.4,<2.0.0)
Requires-Dist: pyproj (>=3.0.1,<4.0.0)
Requires-Dist: pyshp (>=2.1.3,<3.0.0)
Requires-Dist: scipy (>=1.6.2,<2.0.0)
Requires-Dist: seaborn (>=0.11.1,<0.12.0)
Project-URL: Repository, https://gitlab.tudelft.nl/nwang1/grim
